tracardi_track_client/__init__.py
tracardi_track_client/tracker.py
tracardi_track_client/model/__init__.py
tracardi_track_client/model/browser_context.py
tracardi_track_client/model/credentials.py
tracardi_track_client/model/entity.py
tracardi_track_client/model/event_payload.py
tracardi_track_client/model/metadata.py
tracardi_track_client/model/operation.py
tracardi_track_client/model/payload_options.py
tracardi_track_client/model/profile.py
tracardi_track_client/model/resource.py
tracardi_track_client/model/time.py
tracardi_track_client/model/token.py
tracardi_track_client/model/tracker_payload.py
tracardi_track_client/model/web_page.py
tracardi_track_client/model/__pycache__/__init__.cpython-38.pyc
tracardi_track_client/model/__pycache__/browser_context.cpython-38.pyc
tracardi_track_client/model/__pycache__/entity.cpython-38.pyc
tracardi_track_client/model/__pycache__/event_payload.cpython-38.pyc
tracardi_track_client/model/__pycache__/payload_options.cpython-38.pyc
tracardi_track_client/model/__pycache__/time.cpython-38.pyc
tracardi_track_client/model/__pycache__/tracker_payload.cpython-38.pyc
tracardi_track_client-0.7.3.dist-info/METADATA
tracardi_track_client-0.7.3.dist-info/WHEEL
tracardi_track_client-0.7.3.dist-info/top_level.txt
tracardi_track_client-0.7.3.dist-info/RECORD
