Metadata-Version: 2.1
Name: tracardi-track-client
Version: 0.7.3
Summary: Tracardi Customer Data Platform
Author: Risto Kowaczewski
Author-email: risto.kowaczewski@gmail.com
Keywords: tracardi
Classifier: Programming Language :: Python :: 3
Classifier: License :: OSI Approved :: MIT License
Classifier: Operating System :: OS Independent
Requires-Python: >=3.8
Requires-Dist: requests
Requires-Dist: pydantic
